nucml/__init__.py
nucml/config.py
nucml/configure.py
nucml/datasets.py
nucml/general_utilities.py
nucml/processing.py
nucml/setup.py
nucml/ace/__init__.py
nucml/ace/data_utilities.py
nucml/ace/plot.py
nucml/ace/plotting_utilities.py
nucml/ame/__init__.py
nucml/ame/parsing.py
nucml/ame/parsing_utilities.py
nucml/ensdf/__init__.py
nucml/ensdf/data_utilities.py
nucml/ensdf/parsing.py
nucml/ensdf/plot.py
nucml/evaluation/__init__.py
nucml/evaluation/data_utilities.py
nucml/evaluation/plot.py
nucml/evaluation/objects/Element_AAA.pkl
nucml/exfor/__init__.py
nucml/exfor/data_utilities.py
nucml/exfor/parsing.py
nucml/exfor/plot.py
nucml/exfor/objects/Element_AAA.pkl
nucml/model/__init__.py
nucml/model/building_utils.py
nucml/model/dt.py
nucml/model/model_building.py
nucml/model/plot.py
nucml/model/training.py
nucml/model/utilities.py
nucml/objects/EXFOR_AME_dtypes.pkl
nucml/objects/Element_AAA.pkl
nucml/objects/__init__.py
nucml/objects/element_basic_dict.pkl
nucml/objects/exfor_elements_list.pkl
nucml/objects/key_ZAN_AME_value_el_dict.pkl
nucml/objects/key_ZAN_EXFOR_value_el_dict.pkl
nucml/objects/key_element_value_ZAN_dict.pkl
nucml/objects/objects.py
nucml/plot/__init__.py
nucml/plot/utilities.py
nucml-1.0.5.dev1.dist-info/LICENSE.txt
nucml-1.0.5.dev1.dist-info/METADATA
nucml-1.0.5.dev1.dist-info/WHEEL
nucml-1.0.5.dev1.dist-info/top_level.txt
nucml-1.0.5.dev1.dist-info/RECORD
