Metadata-Version: 2.1
Name: nucml
Version: 1.0.5.dev1
Summary: ML-oriented tools for navigating the nuclear data evaluation pipeline.
Home-page: https://github.com/pedrojrv/nucml
Author: Pedro Jr Vicente Valdez
Author-email: pedro.vicentevz@berkeley.edu
License: GNU General Public License v3 or later (GPLv3+)
Project-URL: Documentation, https://pedrojrv.github.io/nucml
Keywords: nuclear ml nucml nuclearml nucleardata data cross section
Platform: UNKNOWN
Classifier: Programming Language :: Python :: 3
Classifier: License :: OSI Approved :: GNU General Public License v3 or later (GPLv3+)
Classifier: Operating System :: OS Independent
Classifier: Development Status :: 3 - Alpha
Requires-Python: >=3.6
Requires-Dist: natsort
Requires-Dist: pandas
Requires-Dist: plotly
Requires-Dist: matplotlib
Requires-Dist: scikit-learn
Requires-Dist: seaborn
Requires-Dist: imageio
Requires-Dist: wandb
Requires-Dist: google-cloud-bigquery
